<annotation verified="yes">
    <folder>Annotation</folder>
    <filename>0622.jpg</filename>
    <path>gesture-PascalVOC-export/Annotations/0622.jpg</path>
    <source>
        <database>Unknown</database>
    </source>
    <size>
        <width>400</width>
        <height>300</height>
        <depth>3</depth>
    </size>
    <segmented>0</segmented>
    <object>
    <name>剪刀</name>
    <pose>Unspecified</pose>
    <truncated>0</truncated>
    <difficult>0</difficult>
    <bndbox>
        <xmin>153.27564894932016</xmin>
        <ymin>81.7339373970346</ymin>
        <xmax>210.13597033374538</xmax>
        <ymax>174.6499176276771</ymax>
    </bndbox>
</object>
</annotation>
