<annotation verified="yes">
    <folder>Annotation</folder>
    <filename>0829.jpg</filename>
    <path>gesture-PascalVOC-export/Annotations/0829.jpg</path>
    <source>
        <database>Unknown</database>
    </source>
    <size>
        <width>400</width>
        <height>300</height>
        <depth>3</depth>
    </size>
    <segmented>0</segmented>
    <object>
    <name>枪</name>
    <pose>Unspecified</pose>
    <truncated>0</truncated>
    <difficult>0</difficult>
    <bndbox>
        <xmin>192.8263988522238</xmin>
        <ymin>114.3642447418738</ymin>
        <xmax>259.97130559540886</xmax>
        <ymax>186.06596558317398</ymax>
    </bndbox>
</object>
</annotation>
