<annotation verified="yes">
    <folder>Annotation</folder>
    <filename>1009.jpg</filename>
    <path>gesture-PascalVOC-export/Annotations/1009.jpg</path>
    <source>
        <database>Unknown</database>
    </source>
    <size>
        <width>400</width>
        <height>300</height>
        <depth>3</depth>
    </size>
    <segmented>0</segmented>
    <object>
    <name>小指</name>
    <pose>Unspecified</pose>
    <truncated>0</truncated>
    <difficult>0</difficult>
    <bndbox>
        <xmin>185.36585365853657</xmin>
        <ymin>95.43499043977056</ymin>
        <xmax>235.8680057388809</xmax>
        <ymax>172.29923518164435</ymax>
    </bndbox>
</object>
</annotation>
